et_foo/__init__.py
et_foo/tests/__init__.py
et_foo/tests/test_et_foo.py
et_foo-0.1.1.dist-info/entry_points.txt
et_foo-0.1.1.dist-info/LICENSE
et_foo-0.1.1.dist-info/WHEEL
et_foo-0.1.1.dist-info/METADATA
et_foo-0.1.1.dist-info/RECORD
