Metadata-Version: 2.1
Name: et-foo
Version: 0.1.1
Summary: <Enter a one-sentence description of this project here.>
Home-page: https://github.com/etijskens/et-foo
License: MIT
Keywords: packaging,poetry
Author: Engelbert Tijskens
Author-email: engelbert.tijskens@uantwerpen.be
Requires-Python: >=3.7,<4.0
Classifier: License :: OSI Approved :: MIT License
Classifier: Programming Language :: Python :: 3
Classifier: Programming Language :: Python :: 3.7
Classifier: Programming Language :: Python :: 3.8
Requires-Dist: click (>=7.0,<8.0)
Requires-Dist: cookiecutter (>=1.6.0,<2.0.0)
Project-URL: Repository, https://github.com/etijskens/et-foo
